# ✅javap命令的作用是什么？

> 题号：0401 ｜ 分类：02_JVM

---

## 速记

- javap是jdk自带的一个工具，可以对代码反编译，也可以查看java编译器生成的字节码。
- 一般情况下，很少有人使用javap对class文件进行反编译，因为有很多成熟的反编译工具可以使用，比如jad。

### 使用

- javap命令分解一个class文件，它根据options来决定到底输出什么。

```c
public class JavapTest {
    public static void main(String[] args) {
        String info = "this is hollis testing javap";

        System.out.println(info);

        Integer integer = new Integer(1);

        String string = integer.toString();

        String string1 = "Hollis" + "Chuang";
    }
}

```

- 在命令行上键入javap DocFooter后，输出结果如下：

```c
➜  javap JavapTest

Compiled from "JavapTest.java"
public class JavapTest {
  public JavapTest();
  public static void main(java.lang.String[]);
}

```

- 如果加入了-c，即javap -c JavapTest，那么输出结果如下：

```c
➜  javap -c JavapTest

Compiled from "JavapTest.java"
public class JavapTest {
  public JavapTest();
    Code:
       0: aload_0
       1: invokespecial #1                  // Method java/lang/Object."<init>":()V
       4: return

  public static void main(java.lang.String[]);
    Code:
       0: ldc           #2                  // String this is hollis testing javap
       2: astore_1
       3: getstatic     #3                  // Field java/lang/System.out:Ljava/io/PrintStream;
       6: aload_1
       7: invokevirtual #4                  // Method java/io/PrintStream.println:(Ljava/lang/String;)V
      10: new           #5                  // class java/lang/Integer
      13: dup
      14: iconst_1
      15: invokespecial #6                  // Method java/lang/Integer."<init>":(I)V
      18: astore_2
      19: aload_2
      20: invokevirtual #7                  // Method java/lang/Integer.toString:()Ljava/lang/String;
      23: astore_3
      24: ldc           #8                  // String HollisChuang
      26: astore        4
      28: return
}

```

- 其中的ldf dup astore都是一条条指令。
- 如果想要查看编译后的class文件中的常量池信息，可以加上-v

```c
➜  javap -c -v JavapTest
Classfile /Users/hollis/workspace/chaojue/HLab/src/main/java/JavapTest.class
  Last modified 2023-10-9; size 578 bytes
  MD5 checksum 7cc427c7df602940ea859d1847034844
  Compiled from "JavapTest.java"
public class JavapTest
  minor version: 0
  major version: 52
  flags: ACC_PUBLIC, ACC_SUPER
Constant pool:
   #1 = Methodref          #10.#19        // java/lang/Object."<init>":()V
   #2 = String             #20            // this is hollis testing javap
   #3 = Fieldref           #21.#22        // java/lang/System.out:Ljava/io/PrintStream;
   #4 = Methodref          #23.#24        // java/io/PrintStream.println:(Ljava/lang/String;)V
   #5 = Class              #25            // java/lang/Integer
// ...省略
```

- 上面的Constant pool部分就是常量池，可以看到其中包含了两个字符串常量：
- 通过上面的结果我们也可以知道，javap并没有将字节码反编译成java文件，而是生成了一种我们可以看得懂字节码。
- 一般情况下我们会用到javap命令的时候不多，一般只有在真的需要看字节码的时候才会用到。
